{
"type": "FeatureCollection",
"name": "random_70",
"crs": { "type": "name", "properties": { "name": "urn:ogc:def:crs:OGC:1.3:CRS84" } },
"features": [
{ "type": "Feature", "properties": { "rand_point_id": 0, "Dis No": "2020-0055-BDI", "Year": "2020", "Seq": "0055", "Glide": null, "Disaster Group": "Natural", "Disaster Subgroup": "Hydrological", "Disaster Type": "Flood", "Disaster Subtype": null, "Disaster Subsubtype": null, "Event Name": null, "Country": "Burundi", "ISO": "BDI", "Region": "Eastern Africa", "Continent": "Africa", "Location": "Bujumbura Rural, Bujumbura Mairie, Bubanza Provinces", "Origin": null, "Associated Dis": null, "Associated Dis2": null, "OFDA Response": null, "Appeal": null, "Declaration": null, "Aid Contribution": null, "Dis Mag Value": null, "Dis Mag Scale": "Km2", "Latitude": null, "Longitude": null, "Local Time": null, "River Basin": "Rusizi River", "Start Year": "2020", "Start Month": "1", "Start Day": "28", "End Year": "2020", "End Month": "2", "End Day": "13", "Total Deaths": "3", "No Injured": "19", "No Affected": "9743", "No Homeless": null, "Total Affected": "9762", "Reconstruction Costs ('000 US$)": null, "Insured Damages ('000 US$)": null, "Total Damages ('000 US$)": null, "CPI": null, "Adm Level": "1", "Admin1 Code": "40542;40543;40544", "Admin2 Code": null, "Geo Locations": "Bubanza, Bujumbura Mairie, Bujumbura Rural (Adm1).", "id": 70 }, "geometry": { "type": "Point", "coordinates": [ 29.343885184594271, -3.418954337887925 ] } }
]
}
