{
"type": "FeatureCollection",
"name": "random_66",
"crs": { "type": "name", "properties": { "name": "urn:ogc:def:crs:OGC:1.3:CRS84" } },
"features": [
{ "type": "Feature", "properties": { "rand_point_id": 0, "Dis No": "2019-0645-BDI", "Year": "2019", "Seq": "0645", "Glide": null, "Disaster Group": "Natural", "Disaster Subgroup": "Hydrological", "Disaster Type": "Flood", "Disaster Subtype": null, "Disaster Subsubtype": null, "Event Name": null, "Country": "Burundi", "ISO": "BDI", "Region": "Eastern Africa", "Continent": "Africa", "Location": "Uwinterekwa, Buterere (Bujumba Mairie)", "Origin": null, "Associated Dis": "Slide (land, mud, snow, rock)", "Associated Dis2": null, "OFDA Response": null, "Appeal": null, "Declaration": null, "Aid Contribution": null, "Dis Mag Value": null, "Dis Mag Scale": "Km2", "Latitude": null, "Longitude": null, "Local Time": null, "River Basin": null, "Start Year": "2019", "Start Month": "12", "Start Day": "21", "End Year": "2019", "End Month": "12", "End Day": "28", "Total Deaths": "14", "No Injured": "33", "No Affected": "3740", "No Homeless": null, "Total Affected": "3773", "Reconstruction Costs ('000 US$)": null, "Insured Damages ('000 US$)": null, "Total Damages ('000 US$)": null, "CPI": "100", "Adm Level": "1", "Admin1 Code": "40543", "Admin2 Code": null, "Geo Locations": "Bujumbura Mairie (Adm1).", "id": 66 }, "geometry": { "type": "Point", "coordinates": [ 29.344850553309929, -3.41863091809896 ] } }
]
}
